tests/__init__.py
tests/test_formatter.py
yajl/__init__.py
yet_another_json_logger-0.1.0.dist-info/LICENSE
yet_another_json_logger-0.1.0.dist-info/METADATA
yet_another_json_logger-0.1.0.dist-info/WHEEL
yet_another_json_logger-0.1.0.dist-info/top_level.txt
yet_another_json_logger-0.1.0.dist-info/RECORD
