Metadata-Version: 2.1
Name: yet-another-json-logger
Version: 0.1.0
Summary: A simple JSON logger, used for structured logging
Home-page: https://github.com/buhanec/yet-another-json-logger
Author: Alen Buhanec <alen.buhanec@gmail.com>
License: MIT
Platform: UNKNOWN
Classifier: Topic :: System :: Logging
Classifier: Development Status :: 4 - Beta
Classifier: Programming Language :: Python :: 3
Classifier: Programming Language :: Python :: 3.7
Classifier: Programming Language :: Python :: 3.8
Classifier: Programming Language :: Python :: 3.9
Classifier: License :: OSI Approved :: MIT License
Classifier: Operating System :: OS Independent
Classifier: Typing :: Typed
